super_gradients/__init__.py
super_gradients/convert_recipe_to_code.py
super_gradients/dataset_interfaces.py
super_gradients/evaluate_checkpoint.py
super_gradients/evaluate_from_recipe.py
super_gradients/qat_from_recipe.py
super_gradients/requirements.pro.txt
super_gradients/requirements.txt
super_gradients/resume_experiment.py
super_gradients/train_from_kd_recipe.py
super_gradients/train_from_recipe.py
super_gradients/common/__init__.py
super_gradients/common/deprecate.py
super_gradients/common/object_names.py
super_gradients/common/abstractions/__init__.py
super_gradients/common/abstractions/abstract_logger.py
super_gradients/common/abstractions/mute_processes.py
super_gradients/common/auto_logging/__init__.py
super_gradients/common/auto_logging/auto_logger.py
super_gradients/common/auto_logging/console_logging.py
super_gradients/common/aws_connection/__init__.py
super_gradients/common/aws_connection/aws_connector.py
super_gradients/common/crash_handler/__init__.py
super_gradients/common/crash_handler/crash_handler.py
super_gradients/common/crash_handler/crash_tips.py
super_gradients/common/crash_handler/crash_tips_setup.py
super_gradients/common/crash_handler/exception.py
super_gradients/common/crash_handler/exception_monitoring_setup.py
super_gradients/common/crash_handler/utils.py
super_gradients/common/data_connection/__init__.py
super_gradients/common/data_connection/s3_connector.py
super_gradients/common/data_interface/__init__.py
super_gradients/common/data_interface/adnn_model_repository_data_interface.py
super_gradients/common/data_interface/dataset_data_interface.py
super_gradients/common/data_types/__init__.py
super_gradients/common/data_types/enum/__init__.py
super_gradients/common/data_types/enum/deep_learning_task.py
super_gradients/common/data_types/enum/downsample_mode.py
super_gradients/common/data_types/enum/evaluation_type.py
super_gradients/common/data_types/enum/multi_gpu_mode.py
super_gradients/common/data_types/enum/strict_load.py
super_gradients-3.7.1.dist-info/LICENSE.YOLONAS-POSE.md
super_gradients-3.7.1.dist-info/LICENSE.YOLONAS.md
super_gradients-3.7.1.dist-info/LICENSE.md
super_gradients-3.7.1.dist-info/METADATA
super_gradients-3.7.1.dist-info/WHEEL
super_gradients-3.7.1.dist-info/top_level.txt
super_gradients-3.7.1.dist-info/RECORD
