Metadata-Version: 2.1
Name: super-gradients
Version: 3.7.1
Summary: SuperGradients
Home-page: https://docs.deci.ai/super-gradients/documentation/source/welcome.html
Author: Deci AI
Author-email: rnd@deci.ai
Keywords: Deci,AI,Training,Deep Learning,Computer Vision,PyTorch,SOTA,Recipes,Pre Trained,Models
License-File: LICENSE.YOLONAS-POSE.md
License-File: LICENSE.YOLONAS.md
License-File: LICENSE.md
Requires-Dist: torch >=1.9.0
Requires-Dist: tqdm >=4.57.0
Requires-Dist: boto3 >=1.17.15
Requires-Dist: jsonschema >=3.2.0
Requires-Dist: Deprecated >=1.2.11
Requires-Dist: scipy >=1.6.1
Requires-Dist: matplotlib >=3.3.4
Requires-Dist: psutil >=5.8.0
Requires-Dist: tensorboard >=2.4.1
Requires-Dist: setuptools >=65.5.1
Requires-Dist: coverage ~=5.3.1
Requires-Dist: torchvision >=0.10.0
Requires-Dist: sphinx ~=4.0.2
Requires-Dist: sphinx-rtd-theme
Requires-Dist: torchmetrics ==0.8
Requires-Dist: hydra-core >=1.2.0
Requires-Dist: omegaconf
Requires-Dist: onnxruntime ==1.15.0
Requires-Dist: onnx ==1.15.0
Requires-Dist: pillow >=10.2.0
Requires-Dist: pip-tools >=6.12.1
Requires-Dist: einops ==0.3.2
Requires-Dist: protobuf ==3.20.3
Requires-Dist: treelib ==1.6.1
Requires-Dist: termcolor ==1.1.0
Requires-Dist: packaging >=20.4
Requires-Dist: wheel >=0.38.0
Requires-Dist: pygments >=2.7.4
Requires-Dist: stringcase >=1.2.0
Requires-Dist: numpy <=1.23
Requires-Dist: rapidfuzz
Requires-Dist: json-tricks ==3.16.1
Requires-Dist: onnxsim <1.0,>=0.4.3
Requires-Dist: data-gradients ~=0.3.1
Requires-Dist: albumentations ~=1.3
Requires-Dist: fonttools >=4.43.0
Requires-Dist: werkzeug >=2.3.8
Provides-Extra: pro
Requires-Dist: deci-platform-client >=5.0.0 ; extra == 'pro'
